duckduckgo_translator/__init__.py
duckduckgo_translator/constants.py
duckduckgo_translator/exceptions.py
duckduckgo_translator/models.py
duckduckgo_translator/translator.py
duckduckgo_translator/utils.py
duckduckgo_translator-0.0.2.dist-info/LICENSE
duckduckgo_translator-0.0.2.dist-info/METADATA
duckduckgo_translator-0.0.2.dist-info/WHEEL
duckduckgo_translator-0.0.2.dist-info/top_level.txt
duckduckgo_translator-0.0.2.dist-info/RECORD
