Metadata-Version: 2.1
Name: duckduckgo-translator
Version: 0.0.2
Summary: Duckduckgo Translator
Author-email: metebtg <metebtg@protonmail.com>
Project-URL: Homepage, https://github.com/metebtg/duckduckgo_translator
Project-URL: Bug Tracker, https://github.com/metebtg/duckduckgo_translator/issues
Classifier: Programming Language :: Python :: 3
Classifier: License :: OSI Approved :: MIT License
Classifier: Operating System :: OS Independent
Requires-Python: >=3.7
License-File: LICENSE
